Advanced Counter/src/AdvancedCounter.sv
module AdvancedCounter (
    input wire clk,
    input wire rst,
    input wire en_inc,
    input wire en_dec,
    input wire load,
    input wire hold,
    input wire [3:0] load_value,
    output reg [3:0] count
);

always @(posedge clk) begin
    if (rst == 1'b1) begin
        count <= 4'd0; // Reset condition
    end else if (load == 1'b1) begin
        count <= load_value; // Load new value
    end else if (hold == 1'b1) begin
        count <= count; // Hold current value
    end else begin
        if (en_inc == 1'b1) begin
            count <= count + 1; // Increment condition
        end else if (en_dec == 1'b1) begin
            count <= count - 1; // Decrement condition
        end
    end
end

endmodule

Advanced Counter/sim/AdvancedCounter_tb.sv
`timescale 1ns/1ps

module AdvancedCounter_tb;

    // Testbench Signals
    logic clk;
    logic rst;
    logic en_inc;
    logic en_dec;
    logic load;
    logic hold;
    logic [3:0] load_value;
    logic [3:0] count;

    // Clock Generation 
    always #10 clk = ~clk;

    // DUT Instantiation
    AdvancedCounter DUT (
        .clk(clk),
        .rst(rst),
        .en_inc(en_inc),
        .en_dec(en_dec),
        .load(load),
        .hold(hold),
        .load_value(load_value),
        .count(count)
    );

    // Functional Coverage
    covergroup counter_cg @(posedge clk);
        coverpoint rst { bins active = {1}; } // Reset coverage
        coverpoint load { bins active = {1}; } // Load coverage
        coverpoint hold { bins active = {1}; } // Hold coverage
        coverpoint en_inc { bins active = {1}; } // Increment coverage
        coverpoint en_dec { bins active = {1}; } // Decrement coverage
        coverpoint count {
            bins min_value = {4'b0000};
            bins max_value = {4'b1111};
        } // Min & Max value coverage
    endgroup

    counter_cg cg = new(); // Instantiate coverage

    // Stimulus Task
    task apply_stimulus(
        input logic rst_in,
        input logic load_in,
        input logic hold_in,
        input logic en_inc_in,
        input logic en_dec_in,
        input logic [3:0] load_val
    );
        rst = rst_in;
        load = load_in;
        hold = hold_in;
        en_inc = en_inc_in;
        en_dec = en_dec_in;
        load_value = load_val;
        #20; // Wait for a clock cycle
    endtask

    // Test Sequence
    initial begin
        // Initialize
        clk = 0;
        rst = 0;
        en_inc = 0;
        en_dec = 0;
        load = 0;
        hold = 0;
        load_value = 4'b0000;

        // Monitor Output
        $monitor("Time=%0t | rst=%b | load=%b | hold=%b | en_inc=%b | en_dec=%b | count=%b",
                 $time, rst, load, hold, en_inc, en_dec, count);

        // Reset Test
        apply_stimulus(1, 0, 0, 0, 0, 4'b0000);
        #20;
        apply_stimulus(0, 0, 0, 0, 0, 4'b0000);

        // Load Test
        apply_stimulus(0, 1, 0, 0, 0, 4'b1010);
        #20;
        apply_stimulus(0, 0, 0, 0, 0, 4'b0000);

        // Hold Test
        apply_stimulus(0, 0, 1, 1, 0, 4'b0000);
        #20;

        // Increment Test
        apply_stimulus(0, 0, 0, 1, 0, 4'b0000);
        #40;

        // Decrement Test
        apply_stimulus(0, 0, 0, 0, 1, 4'b0000);
        #40;

        // Simultaneous Increment & Decrement (Should hold value)
        apply_stimulus(0, 0, 0, 1, 1, 4'b0000);
        #40;

        // Boundary Test (Max Value)
        apply_stimulus(0, 1, 0, 0, 0, 4'b1111);
        #20;
        apply_stimulus(0, 0, 0, 1, 0, 4'b0000);
        #40;

        // Boundary Test (Min Value)
        apply_stimulus(0, 1, 0, 0, 0, 4'b0000);
        #20;
        apply_stimulus(0, 0, 0, 0, 1, 4'b0000);
        #40;

        // End Test
        rst = 1'b1;
        #10
        rst = 1'b0;
        #10
        rst = 1'b1;
        $display("Test Completed.");
        $stop;
    end

    initial begin
        $dumpfile("AdvancedCounter.vcd");
        $dumpvars(AdvancedCounter_tb);

    end
endmodule

Advanced Counter/reports/AdvancedCounter.vcd
$date
	Mon Feb 17 22:55:09 2025
$end
$version
	QuestaSim Version 2021.1
$end
$timescale
	1ps
$end

$scope module AdvancedCounter_tb $end
$var reg 1 ! clk $end
$var reg 1 " rst $end
$var reg 1 # en_inc $end
$var reg 1 $ en_dec $end
$var reg 1 % load $end
$var reg 1 & hold $end
$var reg 4 ' load_value [3:0] $end
$var reg 4 ( count [3:0] $end

$scope task apply_stimulus $end
$var reg 1 ) rst_in $end
$var reg 1 * load_in $end
$var reg 1 + hold_in $end
$var reg 1 , en_inc_in $end
$var reg 1 - en_dec_in $end
$var reg 4 . load_val [3:0] $end
$upscope $end

$scope module DUT $end
$var wire 1 / clk $end
$var wire 1 0 rst $end
$var wire 1 1 en_inc $end
$var wire 1 2 en_dec $end
$var wire 1 3 load $end
$var wire 1 4 hold $end
$var wire 1 5 load_value [3] $end
$var wire 1 6 load_value [2] $end
$var wire 1 7 load_value [1] $end
$var wire 1 8 load_value [0] $end
$var reg 4 9 count [3:0] $end
$upscope $end
$upscope $end
$enddefinitions $end
#0
$dumpvars
0!
1"
0#
0$
0%
0&
b0 '
bx (
bx 9
1)
0*
0+
0,
0-
b0 .
08
07
06
05
04
03
02
01
10
0/
$end
#10000
1!
1/
b0 9
b0 (
#20000
0!
0/
#30000
1!
1/
#40000
0)
0"
0!
00
0/
#50000
1!
1/
#60000
1*
b1010 .
1%
b1010 '
0!
13
17
15
0/
#70000
1!
1/
b1010 9
b1010 (
#80000
0!
0/
#90000
1!
1/
#100000
0*
b0 .
0%
b0 '
0!
03
07
05
0/
#110000
1!
1/
#120000
1+
1,
1&
1#
0!
14
11
0/
#130000
1!
1/
#140000
0!
0/
#150000
1!
1/
#160000
0+
0&
0!
04
0/
#170000
1!
1/
b1011 9
b1011 (
#180000
0!
0/
#190000
1!
1/
b1100 9
b1100 (
#200000
0!
0/
#210000
1!
1/
b1101 9
b1101 (
#220000
0,
1-
0#
1$
0!
01
12
0/
#230000
1!
1/
b1100 9
b1100 (
#240000
0!
0/
#250000
1!
1/
b1011 9
b1011 (
#260000
0!
0/
#270000
1!
1/
b1010 9
b1010 (
#280000
1,
1#
0!
11
0/
#290000
1!
1/
b1011 9
b1011 (
#300000
0!
0/
#310000
1!
1/
b1100 9
b1100 (
#320000
0!
0/
#330000
1!
1/
b1101 9
b1101 (
#340000
1*
0,
0-
b1111 .
1%
0#
0$
b1111 '
0!
13
01
02
18
17
16
15
0/
#350000
1!
1/
b1111 9
b1111 (
#360000
0!
0/
#370000
1!
1/
#380000
0*
1,
b0 .
0%
1#
b0 '
0!
03
11
08
07
06
05
0/
#390000
1!
1/
b0 9
b0 (
#400000
0!
0/
#410000
1!
1/
b1 9
b1 (
#420000
0!
0/
#430000
1!
1/
b10 9
b10 (
#440000
1*
0,
1%
0#
0!
13
01
0/
#450000
1!
1/
b0 9
b0 (
#460000
0!
0/
#470000
1!
1/
#480000
0*
1-
0%
1$
0!
03
12
0/
#490000
1!
1/
b1111 9
b1111 (
#500000
0!
0/
#510000
1!
1/
b1110 9
b1110 (
#520000
0!
0/
#530000
1!
1/
b1101 9
b1101 (
#540000
1"
0!
10
0/
#550000
0"
1!
00
1/
b1100 9
b1100 (
#560000
1"
